onkeypress/__init__.py
onkeypress/classes.py
onkeypress/decorators.py
onkeypress/helpers.py
onkeypress-0.0.7.dist-info/METADATA
onkeypress-0.0.7.dist-info/WHEEL
onkeypress-0.0.7.dist-info/licenses/LICENSE
onkeypress-0.0.7.dist-info/RECORD
