Metadata-Version: 2.4
Name: onkeypress
Version: 0.0.7
Summary: A simple program that allows users to make their terminal reactive to keypresses
Project-URL: Homepage, https://github.com/zlliu246/onkeypress
Project-URL: Issues, https://github.com/zlliu246/onkeypress/issues
Author-email: Liu Zuo Lin <zlliu246@gmail.com>
License-File: LICENSE
Classifier: License :: OSI Approved :: MIT License
Classifier: Operating System :: OS Independent
Classifier: Programming Language :: Python :: 3
Requires-Python: >=3.8
Requires-Dist: toggle-cbreak
